word_hunt_solver/__init__.py
word_hunt_solver/solver.py
word_hunt_solver-0.1.2.dist-info/METADATA
word_hunt_solver-0.1.2.dist-info/WHEEL
word_hunt_solver-0.1.2.dist-info/entry_points.txt
word_hunt_solver-0.1.2.dist-info/licenses/LICENSE
word_hunt_solver-0.1.2.dist-info/RECORD
