Metadata-Version: 2.4
Name: word-hunt-solver
Version: 0.1.2
Summary: a minimilistic solver for imessage's game pigeon word hunt game.
Author: Jake
License: MIT License
License-File: LICENSE
Requires-Python: >=3.8
Requires-Dist: english-words==2.0.1
